pyculiarity/__init__.py
pyculiarity/date_utils.py
pyculiarity/detect_anoms.py
pyculiarity/detect_ts.py
pyculiarity/detect_vec.py
pyculiarity/r_stl.py
pyculiarity-0.0.2.dist-info/DESCRIPTION.rst
pyculiarity-0.0.2.dist-info/METADATA
pyculiarity-0.0.2.dist-info/metadata.json
pyculiarity-0.0.2.dist-info/RECORD
pyculiarity-0.0.2.dist-info/top_level.txt
pyculiarity-0.0.2.dist-info/WHEEL
