Metadata-Version: 2.0
Name: pyculiarity
Version: 0.0.2
Summary: A Python port of Twitter's AnomalyDetection R Package.
Home-page: https://github.com/nicolasmiller/pyculiarity
Author: Nicolas Steven Miller
Author-email: nicolasmiller@gmail.com
License: GPL
Keywords: data anomaly detection pandas timeseries
Platform: UNKNOWN
Classifier: Development Status :: 3 - Alpha
Classifier: Intended Audience :: Developers
Classifier: Topic :: Scientific/Engineering
Classifier: License :: OSI Approved :: GNU General Public License v3 (GPLv3)
Classifier: Programming Language :: Python :: 2.7
Requires-Dist: numpy
Requires-Dist: scipy
Requires-Dist: pandas
Requires-Dist: pytz
Requires-Dist: statsmodels
Requires-Dist: rpy2
Provides-Extra: test
Requires-Dist: nose; extra == 'test'
Requires-Dist: mock; extra == 'test'
